ena_utils/__init__.py
ena_utils/__main__.py
ena_utils/experiment.py
ena_utils/ftp.py
ena_utils/project.py
ena_utils/run.py
ena_utils/sample.py
ena_utils/submission.py
ena_utils-0.2.1.dist-info/LICENSE
ena_utils-0.2.1.dist-info/METADATA
ena_utils-0.2.1.dist-info/WHEEL
ena_utils-0.2.1.dist-info/entry_points.txt
ena_utils-0.2.1.dist-info/top_level.txt
ena_utils-0.2.1.dist-info/RECORD
