Metadata-Version: 2.1
Name: ena-utils
Version: 0.2.1
Summary: A simple CLI toolbox to use the European Nucleotide Archive (ENA)
Home-page: https://github.com/auwerxlab/ena-utils
Author: Laboratory of Integrative System Physiology (LISP) at EPFL
Author-email: alexis.rapin@epfl.ch
License: Apache License 2.0
Download-URL: https://github.com/auwerxlab/ena-utils/archive/v0.2.1.tar.gz
Platform: UNKNOWN
Requires-Dist: click (>=7.0)
Requires-Dist: pandas (>=1.1.0)
Requires-Dist: xmltodict (>=0.12.0)
